<?xml version="1.0" encoding="UTF-8" standalone="yes"?>
<imgdir name="9960417.img">
    <imgdir name="info">
        <int name="grade" value="0"/>
        <int name="range" value="600"/>
        <imgdir name="skill">
            <int name="id" value="805"/>
            <int name="effectAfter" value="1080"/>
        </imgdir>
    </imgdir>
    <imgdir name="move">
        <string name="link" value="move"/>
    </imgdir>
    <imgdir name="stand">
        <string name="link" value="stand"/>
    </imgdir>
    <imgdir name="jump">
        <canvas name="0" width="167" height="121">
            <vector name="origin" x="77" y="130"/>
            <vector name="lt" x="-74" y="-118"/>
            <vector name="rb" x="74" y="7"/>
            <vector name="head" x="-3" y="-107"/>
            <int name="delay" value="120"/>
        </canvas>
    </imgdir>
    <imgdir name="fly">
        <string name="link" value="move"/>
    </imgdir>
    <imgdir name="attack">
        <string name="link" value="attack1"/>
    </imgdir>
    <imgdir name="skill">
        <string name="link" value="skill1"/>
    </imgdir>
</imgdir>
